ripserplusplus/Ripser_plusplus_Converter.py
ripserplusplus/__init__.py
ripserplusplus/phmap.dll
ripserplusplus/pyripser++.dll
ripserplusplus-1.1.2.dist-info/LICENSE
ripserplusplus-1.1.2.dist-info/METADATA
ripserplusplus-1.1.2.dist-info/WHEEL
ripserplusplus-1.1.2.dist-info/top_level.txt
ripserplusplus-1.1.2.dist-info/RECORD
