Metadata-Version: 2.1
Name: ripserplusplus
Version: 1.1.2
Summary: Python binding for Ripser++.
Home-page: https://github.com/simonzhang00/ripser-plusplus
Author: Simon Zhang - Ripser++, Ryan DeMilt, Birkan Gokbag, Simon Zhang - Python Binding
Author-email: szhang31415@gmail.com, demilt.ryan@gmail.com, birkan.gokbag@gmail.com 
License: License :: OSI Approved :: MIT License
Platform: UNKNOWN
Classifier: Programming Language :: Python
Classifier: Operating System :: POSIX :: Linux
Classifier: Operating System :: Microsoft :: Windows
Requires-Dist: cmake
Requires-Dist: numpy
Requires-Dist: scipy
